runpod_ssh/VERSION
runpod_ssh/__init__.py
runpod_ssh/cli.py
runpod_ssh/client.py
runpod_ssh/config.py
runpod_ssh/models.py
runpod_ssh-0.2.0.dist-info/METADATA
runpod_ssh-0.2.0.dist-info/WHEEL
runpod_ssh-0.2.0.dist-info/entry_points.txt
runpod_ssh-0.2.0.dist-info/RECORD
